dippy/__init__.py
dippy/algorithms/convert.py
dippy/algorithms/dft.py
dippy/algorithms/dithering.py
dippy/algorithms/filtering.py
dippy/algorithms/kmeans.py
dippy/algorithms/match.py
dippy/algorithms/resize.py
dippy/utils/io.py
dippy/utils/jpeg.py
dippy/utils/print.py
dip_python-0.1.5.dist-info/METADATA
dip_python-0.1.5.dist-info/WHEEL
dip_python-0.1.5.dist-info/top_level.txt
dip_python-0.1.5.dist-info/RECORD
