Metadata-Version: 2.1
Name: dip-python
Version: 0.1.5
Summary: Digital Image Processing in Python
Home-page: https://github.com/R1nY1x1/dippy
Author: RinYixi
Author-email: hayashi0241@gmail.com
License: MIT
Keywords: dippy
Platform: UNKNOWN
Classifier: License :: OSI Approved :: MIT License
Classifier: Programming Language :: Python :: 3.8
Requires-Python: >=3.6
Requires-Dist: numpy
